pyequations/__init__.py
pyequations/context_stack.py
pyequations/decorators.py
pyequations/generate_units_subs.py
pyequations/inheritables.py
pyequations/utils.py
pyequations-0.1.4.dist-info/LICENSE
pyequations-0.1.4.dist-info/METADATA
pyequations-0.1.4.dist-info/WHEEL
pyequations-0.1.4.dist-info/RECORD
